{
    "name": "Elements-AI-Necklace Development",
    "dockerComposeFile": "docker-compose.yml",
    "service": "workspace",
    "workspaceFolder": "/workspace",
    "customizations": {
        "vscode": {
            "extensions": [
                "ms-python.python",
                "ms-python.vscode-pylance",
                "ms-python.black-formatter",
                "dbaeumer.vscode-eslint",
                "esbenp.prettier-vscode",
                "ms-vscode.cpptools",
                "ms-vscode.cmake-tools",
                "github.copilot",
                "github.vscode-github-actions",
                "eamodio.gitlens"
            ]
        }
    },
    "remoteUser": "vscode",
    "features": {
        "ghcr.io/devcontainers/features/docker-in-docker:2": {},
        "ghcr.io/devcontainers/features/github-cli:1": {}
    }
}